<questions>
      <question id="LC-ECQA2002-00002-01">
          <text>東海地方に含まれる県はどこ？</text>
          <meta>
      <A.memo/>
      <B1>どこ</B1>
      <B2>A</B2>
      <B3>地理</B3>
      <B4>県</B4>
      <B5>東海地方</B5>
      <B6>国内地域名</B6>
      <B7>県</B7>
      <B.memo/>
      <C1>Select ?x
Where {
東海地方	所属県		?x.
}</C1>
	    <C2/>
      <Cmemo/>
      <D2>複数</D2>
      <D3>都道府県州名</D3>
      <D.memo/>
      <E1>Y</E1>
      <E2>a</E2>
      <E3>東海地方</E3>
      <E4>冒頭</E4>
      <E5>愛知県、岐阜県、三重県、静岡県の4県を指す場合と、愛知県、岐阜県、三重県の3県を指す場合がある。</E5>
      <E6/>
      <E7/>
      <E8/>
      <Ememo/>
      <F1>Y</F1>
      <F2>Select ?province
Where {
?province jwo-prop:地方 jwo-instance:東海地方.
?province rdf:type jwo-class:県
}</F2>
      <Fmemo>タイプ不足により解答が不完全</Fmemo>
    </meta>
          <answers>
      <answer>愛知県</answer>
      <answer>岐阜県</answer>
      <answer>三重県</answer>
      <answer>静岡県</answer>
    </answers>
          <annotations>
          <annotation type="juman/knp" annotator="JiggParser">
          <questionType>where</questionType>
          <parses><parse>
            <root>
  <document id="d0">
    <sentences>
      <sentence id="s0">
        東海地方に含まれる県はどこ？。
        <tokens>
          <token id="s0_tok0" surf="東海" pos="名詞" pos1="地名" inflectionType="*" inflectionForm="*" base="東海" reading="とうかい" posId="6" pos1Id="4" inflectionTypeId="0" inflectionFormId="0" features="&quot;代表表記:東海/とうかい 地名:日本:愛知県:市&quot; &lt;代表表記:東海/とうかい&gt;&lt;地名:日本:地方&gt;&lt;正規化代表表記:東海/とうかい&gt;&lt;品曖&gt;&lt;ALT-東海-とうかい-東海-6-4-0-0-&quot;代表表記:東海/とうかい 地名:日本:地方&quot;&gt;&lt;品曖-地名&gt;&lt;文頭&gt;&lt;漢字&gt;&lt;かな漢字&gt;&lt;名詞相当語&gt;&lt;自立&gt;&lt;内容語&gt;&lt;タグ単位始&gt;&lt;文節始&gt;&lt;固有キー&gt;&lt;NE:LOCATION:S&gt;"/>
          <token id="s0_tok1" surf="地方" pos="名詞" pos1="普通名詞" inflectionType="*" inflectionForm="*" base="地方" reading="ちほう" posId="6" pos1Id="1" inflectionTypeId="0" inflectionFormId="0" features="&quot;代表表記:地方/ちほう 地名末尾 カテゴリ:場所-その他&quot; &lt;代表表記:地方/ちほう&gt;&lt;地名末尾&gt;&lt;カテゴリ:場所-その他&gt;&lt;正規化代表表記:地方/ちほう&gt;&lt;Wikipedia上位語:地方/ちほう:0-1&gt;&lt;Wikipediaエントリ:東海地方:0-1&gt;&lt;漢字&gt;&lt;かな漢字&gt;&lt;名詞相当語&gt;&lt;自立&gt;&lt;複合←&gt;&lt;内容語&gt;&lt;タグ単位始&gt;&lt;文節主辞&gt;"/>
          <token id="s0_tok2" surf="に" pos="助詞" pos1="格助詞" inflectionType="*" inflectionForm="*" base="に" reading="に" posId="9" pos1Id="1" inflectionTypeId="0" inflectionFormId="0" features="NIL &lt;かな漢字&gt;&lt;ひらがな&gt;&lt;付属&gt;"/>
          <token id="s0_tok3" surf="含ま" pos="動詞" pos1="*" inflectionType="子音動詞マ行" inflectionForm="未然形" base="含む" reading="ふくま" posId="2" pos1Id="0" inflectionTypeId="9" inflectionFormId="3" features="&quot;代表表記:含む/ふくむ&quot; &lt;代表表記:含む/ふくむ&gt;&lt;正規化代表表記:含む/ふくむ&gt;&lt;かな漢字&gt;&lt;活用語&gt;&lt;自立&gt;&lt;内容語&gt;&lt;タグ単位始&gt;&lt;文節始&gt;&lt;文節主辞&gt;"/>
          <token id="s0_tok4" surf="れる" pos="接尾辞" pos1="動詞性接尾辞" inflectionType="母音動詞" inflectionForm="基本形" base="れる" reading="れる" posId="14" pos1Id="7" inflectionTypeId="1" inflectionFormId="2" features="&quot;代表表記:れる/れる&quot; &lt;代表表記:れる/れる&gt;&lt;正規化代表表記:れる/れる&gt;&lt;かな漢字&gt;&lt;ひらがな&gt;&lt;活用語&gt;&lt;付属&gt;"/>
          <token id="s0_tok5" surf="県" pos="名詞" pos1="普通名詞" inflectionType="*" inflectionForm="*" base="県" reading="けん" posId="6" pos1Id="1" inflectionTypeId="0" inflectionFormId="0" features="&quot;代表表記:県/けん 漢字読み:音 住所末尾 カテゴリ:組織・団体;場所-その他 ドメイン:政治&quot; &lt;代表表記:県/けん&gt;&lt;漢字読み:音&gt;&lt;住所末尾&gt;&lt;カテゴリ:組織・団体;場所-その他&gt;&lt;ドメイン:政治&gt;&lt;正規化代表表記:県/けん&gt;&lt;漢字&gt;&lt;かな漢字&gt;&lt;名詞相当語&gt;&lt;自立&gt;&lt;内容語&gt;&lt;タグ単位始&gt;&lt;文節始&gt;&lt;文節主辞&gt;"/>
          <token id="s0_tok6" surf="は" pos="助詞" pos1="副助詞" inflectionType="*" inflectionForm="*" base="は" reading="は" posId="9" pos1Id="2" inflectionTypeId="0" inflectionFormId="0" features="NIL &lt;かな漢字&gt;&lt;ひらがな&gt;&lt;付属&gt;"/>
          <token id="s0_tok7" surf="どこ" pos="指示詞" pos1="名詞形態指示詞" inflectionType="*" inflectionForm="*" base="どこ" reading="どこ" posId="7" pos1Id="1" inflectionTypeId="0" inflectionFormId="0" features="&quot;代表表記:どこ/どこ&quot; &lt;代表表記:どこ/どこ&gt;&lt;正規化代表表記:どこ/どこ&gt;&lt;表現文末&gt;&lt;疑問詞&gt;&lt;かな漢字&gt;&lt;ひらがな&gt;&lt;自立&gt;&lt;内容語&gt;&lt;タグ単位始&gt;&lt;文節始&gt;&lt;文節主辞&gt;"/>
          <token id="s0_tok8" surf="？" pos="特殊" pos1="記号" inflectionType="*" inflectionForm="*" base="？" reading="？" posId="1" pos1Id="5" inflectionTypeId="0" inflectionFormId="0" features="NIL &lt;記英数カ&gt;&lt;英記号&gt;&lt;記号&gt;&lt;付属&gt;"/>
          <token id="s0_tok9" surf="。" pos="特殊" pos1="句点" inflectionType="*" inflectionForm="*" base="。" reading="。" posId="1" pos1Id="1" inflectionTypeId="0" inflectionFormId="0" features="NIL &lt;文末&gt;&lt;英記号&gt;&lt;記号&gt;&lt;付属&gt;"/>
        </tokens>
        <basicPhrases>
          <basicPhrase id="s0_bp0" tokens="s0_tok0" features="&lt;文節内&gt;&lt;係:文節内&gt;&lt;文頭&gt;&lt;地名疑&gt;&lt;体言&gt;&lt;名詞項候補&gt;&lt;先行詞候補&gt;&lt;正規化代表表記:東海/とうかい&gt;&lt;NE:LOCATION:東海&gt;&lt;照応詞候補:東海&gt;&lt;EID:0&gt;"/>
          <basicPhrase id="s0_bp1" tokens="s0_tok1 s0_tok2" features="&lt;地名&gt;&lt;ニ&gt;&lt;助詞&gt;&lt;体言&gt;&lt;係:ニ格&gt;&lt;区切:0-0&gt;&lt;格要素&gt;&lt;連用要素&gt;&lt;名詞項候補&gt;&lt;先行詞候補&gt;&lt;SM-場所&gt;&lt;正規化代表表記:地方/ちほう&gt;&lt;Wikipedia上位語:地方/ちほう&gt;&lt;Wikipediaエントリ:東海地方&gt;&lt;照応詞候補:東海地方&gt;&lt;解析格:ニ&gt;&lt;EID:1&gt;"/>
          <basicPhrase id="s0_bp2" tokens="s0_tok3 s0_tok4" features="&lt;態:受動&gt;&lt;〜られる&gt;&lt;連体修飾&gt;&lt;用言:動&gt;&lt;係:連格&gt;&lt;レベル:B&gt;&lt;区切:0-5&gt;&lt;ID:（動詞連体）&gt;&lt;連体節&gt;&lt;動態述語&gt;&lt;正規化代表表記:含む/ふくむ&gt;&lt;用言代表表記:含む/ふくむ+れる/れる&gt;&lt;時制-未来&gt;&lt;格関係1:ニ:地方&gt;&lt;格関係3:ガ:県&gt;&lt;格解析結果:含む/ふくむ+れる/れる:動4:ガ/N/県/3/0/1;ヲ/U/-/-/-/-;ニ/C/地方/1/0/1;ト/U/-/-/-/-;デ/U/-/-/-/-;カラ/U/-/-/-/-;ヨリ/U/-/-/-/-;マデ/U/-/-/-/-;ヘ/U/-/-/-/-;時間/U/-/-/-/-;外の関係/U/-/-/-/-;ノ/U/-/-/-/-;修飾/U/-/-/-/-;ガ２/U/-/-/-/-;ニツク/U/-/-/-/-;トスル/U/-/-/-/-;ニクワエル/U/-/-/-/-;ニヨル/U/-/-/-/-;ヲハジメル/U/-/-/-/-;ニカンスル/U/-/-/-/-&gt;&lt;正規化格解析結果-0:含む/ふくむ:動23:ノ/N/県/3/0/1;ニ/C/地方/1/0/1&gt;&lt;EID:2&gt;&lt;述語項構造:含む/ふくむ+れる/れる:動3:ガ２/N/県/3;ニ/C/東海地方/1&gt;">
</basicPhrase>
          <basicPhrase id="s0_bp3" tokens="s0_tok5 s0_tok6" features="&lt;SM-主体&gt;&lt;SM-組織&gt;&lt;ハ&gt;&lt;助詞&gt;&lt;体言&gt;&lt;一文字漢字&gt;&lt;係:未格&gt;&lt;提題&gt;&lt;区切:3-5&gt;&lt;主題表現&gt;&lt;格要素&gt;&lt;連用要素&gt;&lt;名詞項候補&gt;&lt;先行詞候補&gt;&lt;正規化代表表記:県/けん&gt;&lt;照応詞候補:県&gt;&lt;解析連格:ガ&gt;&lt;解析格:ガ&gt;&lt;EID:3&gt;"/>
          <basicPhrase id="s0_bp4" tokens="s0_tok7 s0_tok8 s0_tok9" features="&lt;文末&gt;&lt;疑問詞&gt;&lt;句点&gt;&lt;体言&gt;&lt;指示詞&gt;&lt;用言:判&gt;&lt;体言止&gt;&lt;レベル:C&gt;&lt;区切:5-5&gt;&lt;ID:（文末）&gt;&lt;裸名詞&gt;&lt;係:文末&gt;&lt;提題受:30&gt;&lt;主節&gt;&lt;格要素&gt;&lt;連用要素&gt;&lt;状態述語&gt;&lt;判定詞&gt;&lt;名詞項候補&gt;&lt;正規化代表表記:どこ/どこ&gt;&lt;用言代表表記:どこ/どこ&gt;&lt;時制-無時制&gt;&lt;照応詞候補:どこ&gt;&lt;格関係3:ガ:県&gt;&lt;格解析結果:どこ/どこ:判36:ガ/N/県/3/0/1;外の関係/U/-/-/-/-&gt;&lt;EID:4&gt;&lt;述語項構造:どこ/どこ:判7:ガ/N/県/3&gt;"/>
        </basicPhrases>
        <chunks>
          <chunk id="s0_chu0" tokens="s0_tok0 s0_tok1 s0_tok2" features="&lt;文頭&gt;&lt;地名&gt;&lt;ニ&gt;&lt;助詞&gt;&lt;体言&gt;&lt;係:ニ格&gt;&lt;区切:0-0&gt;&lt;格要素&gt;&lt;連用要素&gt;&lt;正規化代表表記:東海/とうかい+地方/ちほう&gt;&lt;主辞代表表記:地方/ちほう&gt;"/>
          <chunk id="s0_chu1" tokens="s0_tok3 s0_tok4" features="&lt;態:受動&gt;&lt;〜られる&gt;&lt;連体修飾&gt;&lt;用言:動&gt;&lt;係:連格&gt;&lt;レベル:B&gt;&lt;区切:0-5&gt;&lt;ID:（動詞連体）&gt;&lt;連体節&gt;&lt;動態述語&gt;&lt;正規化代表表記:含む/ふくむ&gt;&lt;主辞代表表記:含む/ふくむ&gt;"/>
          <chunk id="s0_chu2" tokens="s0_tok5 s0_tok6" features="&lt;SM-主体&gt;&lt;SM-組織&gt;&lt;ハ&gt;&lt;助詞&gt;&lt;体言&gt;&lt;一文字漢字&gt;&lt;係:未格&gt;&lt;提題&gt;&lt;区切:3-5&gt;&lt;主題表現&gt;&lt;格要素&gt;&lt;連用要素&gt;&lt;正規化代表表記:県/けん&gt;&lt;主辞代表表記:県/けん&gt;"/>
          <chunk id="s0_chu3" tokens="s0_tok7 s0_tok8 s0_tok9" features="&lt;文末&gt;&lt;疑問詞&gt;&lt;句点&gt;&lt;体言&gt;&lt;指示詞&gt;&lt;用言:判&gt;&lt;体言止&gt;&lt;レベル:C&gt;&lt;区切:5-5&gt;&lt;ID:（文末）&gt;&lt;裸名詞&gt;&lt;係:文末&gt;&lt;提題受:30&gt;&lt;主節&gt;&lt;格要素&gt;&lt;連用要素&gt;&lt;状態述語&gt;&lt;正規化代表表記:どこ/どこ&gt;&lt;主辞代表表記:どこ/どこ&gt;"/>
        </chunks>
        <basicPhraseDependencies root="s0_bp4">
          <basicPhraseDependency id="s0_bpdep0" head="s0_bp1" dependent="s0_bp0" label="D"/>
          <basicPhraseDependency id="s0_bpdep1" head="s0_bp2" dependent="s0_bp1" label="D"/>
          <basicPhraseDependency id="s0_bpdep2" head="s0_bp3" dependent="s0_bp2" label="D"/>
          <basicPhraseDependency id="s0_bpdep3" head="s0_bp4" dependent="s0_bp3" label="D"/>
        </basicPhraseDependencies>
        <dependencies root="s0_chu3">
          <dependency id="s0_dep0" head="s0_chu1" dependent="s0_chu0" label="D"/>
          <dependency id="s0_dep1" head="s0_chu2" dependent="s0_chu1" label="D"/>
          <dependency id="s0_dep2" head="s0_chu3" dependent="s0_chu2" label="D"/>
        </dependencies>
        <caseRelations>
          <caseRelation id="s0_cr0" head="s0_bp2" depend="s0_tok5" label="ガ" flag="N"/>
          <caseRelation id="s0_cr1" head="s0_bp2" depend="unk" label="ヲ" flag="U"/>
          <caseRelation id="s0_cr2" head="s0_bp2" depend="s0_tok1" label="ニ" flag="C"/>
          <caseRelation id="s0_cr3" head="s0_bp2" depend="unk" label="ト" flag="U"/>
          <caseRelation id="s0_cr4" head="s0_bp2" depend="unk" label="デ" flag="U"/>
          <caseRelation id="s0_cr5" head="s0_bp2" depend="unk" label="カラ" flag="U"/>
          <caseRelation id="s0_cr6" head="s0_bp2" depend="unk" label="ヨリ" flag="U"/>
          <caseRelation id="s0_cr7" head="s0_bp2" depend="unk" label="マデ" flag="U"/>
          <caseRelation id="s0_cr8" head="s0_bp2" depend="unk" label="ヘ" flag="U"/>
          <caseRelation id="s0_cr9" head="s0_bp2" depend="unk" label="時間" flag="U"/>
          <caseRelation id="s0_cr10" head="s0_bp2" depend="unk" label="外の関係" flag="U"/>
          <caseRelation id="s0_cr11" head="s0_bp2" depend="unk" label="ノ" flag="U"/>
          <caseRelation id="s0_cr12" head="s0_bp2" depend="unk" label="修飾" flag="U"/>
          <caseRelation id="s0_cr13" head="s0_bp2" depend="unk" label="ガ２" flag="U"/>
          <caseRelation id="s0_cr14" head="s0_bp2" depend="unk" label="ニツク" flag="U"/>
          <caseRelation id="s0_cr15" head="s0_bp2" depend="unk" label="トスル" flag="U"/>
          <caseRelation id="s0_cr16" head="s0_bp2" depend="unk" label="ニクワエル" flag="U"/>
          <caseRelation id="s0_cr17" head="s0_bp2" depend="unk" label="ニヨル" flag="U"/>
          <caseRelation id="s0_cr18" head="s0_bp2" depend="unk" label="ヲハジメル" flag="U"/>
          <caseRelation id="s0_cr19" head="s0_bp2" depend="unk" label="ニカンスル" flag="U"/>
          <caseRelation id="s0_cr20" head="s0_bp4" depend="s0_tok5" label="ガ" flag="N"/>
          <caseRelation id="s0_cr21" head="s0_bp4" depend="unk" label="外の関係" flag="U"/>
        </caseRelations>
        <coreferences>
          <coreference id="s0_coref0" basicPhrases="s0_bp0"/>
          <coreference id="s0_coref1" basicPhrases="s0_bp1"/>
          <coreference id="s0_coref2" basicPhrases="s0_bp2"/>
          <coreference id="s0_coref3" basicPhrases="s0_bp3"/>
          <coreference id="s0_coref4" basicPhrases="s0_bp4"/>
        </coreferences>
        <predicateArgumentRelations>
          <predicateArgumentRelation id="s0_par0" predicate="s0_bp2" argument="s0_coref3" label="ガ２" flag="N"/>
          <predicateArgumentRelation id="s0_par1" predicate="s0_bp2" argument="s0_coref1" label="ニ" flag="C"/>
          <predicateArgumentRelation id="s0_par2" predicate="s0_bp4" argument="s0_coref3" label="ガ" flag="N"/>
        </predicateArgumentRelations>
        <namedEntities>
          <namedEntity id="s0_ne0" tokens="s0_tok0" label="LOCATION"/>
        </namedEntities>
      </sentence>
    </sentences>
  </document>
</root>
            </parse>
          </parses>
          </annotation><annotation annotator="ClueExtractor" type="clue">
          <clues>
            <clue>
              <head>
                    含む
                  </head><deps>
                    <dep>
                        地方
                      </dep><dep>
                        県
                      </dep>
                  </deps><parse>
                    東海地方に含まれる県はどこ？。
                  </parse>
              </clue><clue>
              <head>
                    どこ
                  </head><deps>
                    <dep>
                        県
                      </dep>
                  </deps><parse>
                    東海地方に含まれる県はどこ？。
                  </parse>
              </clue>
          </clues>
        </annotation>
          <annotation type="doc" annotator="SearchDocument">
            <docs>
              <doc>
              <did>
                JBS-19
              </did>
              <dtitle>
                3　下剋上の社会と戦国大名
              </dtitle>
              <dtext>
                
3　下剋上の社会と戦国大名

●産業の発達
　内乱の時期にも，農業はいちじるしく発達した。稲作では，地方の気候にあわせて早稲・中稲・晩稲の品種が栽培され，庶民の食料として東南アジア伝来の米(大唐米)も栽培された。西日本の各地では，麦などを裏作とする二毛作が普及した。肥料として刈敷や草木灰が一般化したため，共同利用となっていた山野の入会権をめぐる争いもおこった。入会権や用水権をめぐる争いでは，同じ利害をもつ農民は，荘園の境界をこえて地域ごとに団結するようになった。また，手工業の原料として，桑・こうぞ・あい・荏胡麻・麻などの栽培もさかんになった。
　漁業を専門とする集団が生まれ，揚浜式の製塩業も普及した。明に対する朝貢品や輸出品として，銅の需要がふえたため，新しい鉱山が数多く開発された。
　京の西陣や博多の絹織物をはじめ，麻織物，綿織物，陶器，紙，酒，油などの生産がすすみ，刀や農具をつくる鍛冶，鋳物業などもさかんになり，手工業は発展をとげた。

〈コラム〉室町時代の職人とは
　職人は刃物・農具・笠・扇など生活に必要なものをつくる人々ばかりでなく，技能，芸能で生活していくものまで，農業以外のあらゆる職種の人々を意味していた。琵琶法師，猿回し，人形遣いなどもふくまれる。職人尽絵屏風・職人風俗絵巻や洛中洛外図屏風などにえがかれている職人を調べてみよう。

●市と座
　産業の発達につれて商業もさかんになった。市の開催日も増加し，応仁の乱後には，月６回の六斎市が一般化した①。都市では，常設の小売店が増加し，特定の商品だけをあつかう専門の市場も生まれた。公家や寺社を本所とする商工業者の座②も，種類や数が増加し，一定地域内での仕入れ・販売の独占権や，領内での関銭免除の特権などを本所からあたえられて，さかんに活動した。
　産業や商品流通の発達とともに，貨幣の流通もさかんになり，年貢の銭納や，段銭・棟別銭など銭納の税も増加した。宋銭や明銭などの輸入銭だけでは，流通量が不足したため，私鋳銭などの不良な銭が使用され，取り引きが混乱した。
　そこで幕府や戦国大名は，しばしばエリ銭令③をだして混乱を防いだが，みずからは銭貨を鋳造しなかった。銭貨の流通により，為替の利用もさかんとなり，酒屋・土倉なども，金融業者として幕府の保護をうけて活躍した。
　商品の輸送とともに，交通も発達した。畿内では大津・坂本・淀など交通の要地に，運送業者(馬借など)が活躍した④。物資の保管や委託販売を業務としてきた問丸は，馬借を支配し，卸売り・運送や商人宿をいとなむ問屋に発展した。
　商品の輸送がはげしくなると，幕府や公家，寺社は，収入をふやす目的で多くの関所を領内の海陸交通の要地に設け，商売物に税(関銭や津料)を課した。

①市では領主から営業を許された市座が設けられ，その地の領主に税をおさめて販売権を確保した商人のみに，営業が認められた。
②西日本の10余か国に灯油の専売権をもっていた大山崎の油座は，石清水八幡宮末社の大山崎離宮八幡宮を本所とした。海路や陸路を通じて運ばれた原料(荏胡麻)から灯油をつくり，京都の公家や寺社，各地の問屋などに販売した。
③流通貨幣(一文銭)の種類を限定し，銭貨間の交換比率を定めた。
④道路が比較的整備された京都と鳥羽，京都と坂本のあいだには，車借が活躍した。

●惣と一揆
　小農民から名主に成長した農民は，武士化した有力名主(地侍)を中心に，荘園の境界をこえて地域的な団結を強めた。このような自治組織としての村落を惣(惣村)とよぶ①。
　惣では，寄合を開いて惣の掟を定め，鎮守社の祭礼，共有地(入会地)や灌漑用水路の管理などについて決定した。年貢も，惣全体の責任で請け負って納入した(地下請，百姓請)。また，代官の罷免や年貢・段銭などの軽減の要求をかかげて，集団で領主と交渉したり，聞きいれられない場合は，逃散や土一揆など，実力行動をとることもあった。
　惣を中心に農民(土民)が団結しておこした土一揆が，やがて幕府に徳政令の発布を要求するなど，社会全体に下剋上の風潮が高まって，幕府の権威は低下した。1428(正長元)年，近江の馬借が，徳政を要求して立ち上がると，京都周辺の農民がこれに参加し，金融業をもいとなむ酒屋や土倉，寺院を襲撃し，借用証文を焼き，質物をうばいかえして，実力による徳政をおこなった(正長の土一揆)。

①惣の団結のもとになったのは，神社の祭祀組織(宮座)であった。

〈史料〉
○惣の掟

　定　今堀 ① 地下(村)掟之事
　合　延徳元(一四八九)年己酉十一月四日
一、他所之人を地下ニ請人(身元保証人)候ハて不可置之事。
一、惣ノ地ト私ノ地トサイメ(境界)相論(争論)これを停止せられをはんぬ。此の上若しハ金ニテすますへし。
一、惣森(惣所有の森)ニテ青木ハ葉かきたる物ハ、村人は村を可落(村の宮座から外し、村人としての権利をうばう)、村人ニテ無物ハ地下ヲハラウヘシ(村から追放する)。
	(日吉神社文書)

①近江国蒲生郡(滋賀県八日市市)にあった惣

○正長の土一揆

［正長元(一四二八)年］九月□日、一天下の土民、蜂起す。徳政と号し(主張し)、酒屋、土倉、寺院等を破却せしめ、雑物等、恣にこれを取り、借銭等(借金証文など)、悉くこれを破る(破棄する)。管領(畠山満家)、これを成敗すと。凡そ亡国の基、これに過ぐるべからず。日本開白(始まり)以来、土民蜂起、是初めなり。	(大乗院日記目録)

●応仁の乱
　武士の社会では，14世紀にはいって単独相続がおこなわれるようになると，所領を相続する惣領の地位(家督)をめぐって，一族のあいだで争いがおこったり，将軍もこれに介入するようになった。
　15世紀なかごろ，８代将軍足利義政は，芸能や造営事業などに浪費をかさねて，守護大名の信望を失うことが多く，幕府の実権は細川勝元と山名持豊(宗全)とに移った。
　このころ将軍家では，義政が跡継ぎと定めた弟の義視と，義政の幼児義尚をたてようとする生母の日野富子とが対立し，また，管領家の斯波氏や畠山氏にも家督をめぐる対立がおこっていたが，それぞれの対立が，細川氏と山名氏との対立に結びついて，1467(応仁元)年，戦いに発展した(応仁の乱)。
　義視・勝元を中心とする東軍と，義尚・持豊を中心とする西軍とは，11年にわたって，京都を中心として戦い，京住いの有力守護大名の多くも，国もとから軍勢を招集し，両軍に分かれて戦いに参加した。戦場となった京都では，畿内の地侍らがやとわれて活躍したが(足軽衆)，かれらの略奪や放火によって，京都の町の大半が焼失した。
　地方では，応仁の乱後も戦乱がつづき，守護代や国人による年貢の横領がいっそうはげしくなり，公家や寺社の経済基盤であった荘園制度はほとんど壊滅状態におちいった。幕府の威令も，わずかに山城一国にしかおよばないありさまとなった。

●下剋上の風潮
　応仁の乱後，幕府の実権は管領の細川氏に移り，16世紀にはいると，細川氏の家臣の三好氏がその実権をうばい，さらに，三好氏もその家臣の松永氏にとってかわられた。こうして室町幕府は，有名無実の存在となった。
　地方でも，応仁の乱後，守護大名の権威がおとろえ，各地で土一揆や国人による国一揆①が活発になってきた。1485(文明17)年，山城南部の国人たちは，集会の決議をもとに，畠山氏の軍勢を国外に退去させることを求め，領主にはとどこおりなく年貢をおさめることを条件に，８年近くのあいだ，国人たちの協議による自治をおこなった(山城の国一揆②)。
　また，畿内，北陸，東海などの地方で，一向宗(浄土真宗)の坊主や門徒の国人は，門徒の農民をひきいて，一向一揆を組織した。なかでも，加賀の金沢を拠点とする一向一揆は，1488(長享２)年，守護の富樫政親を倒し，約１世紀にわたって，門徒の国人が国内を支配した③。
　やがて，生き残った守護大名の領国も，守護代や領国内の有力家臣にうばわれるようになった。このように，下のものが上のものをしのぐ風潮を，下剋上といい，この風潮の高まった応仁の乱のころから，約１世紀にわたる戦乱の時代を，戦国時代とよぶ。

①国一揆は，守護大名に対抗する国人(中小武士団の統率者)の集団行動として，14世紀後半からあらわれた。
②国人たちのなかには，戦国大名の家臣になるものもでて，やがて分裂し，一揆は崩壊していった。
③1580(天正８)年，織田信長の命をうけた柴田勝家によってほろぼされた。

〈史料〉
○山城の国一揆

［文明十七(一四八五)年十二月］十一日、今日山城国人(土豪・地侍)集会す。上ハ六十歳下ハ十五、六歳と云々。同じく一国中の土民等群集す。今度両陣①の時宜を申し定めんが為の故と云々。然るべきか(もっともなことか)。但し又下極上の至也。……
［文明十八年二月］十三日、今日山城国人、平等院に会合す。国中の掟法(国掟)猶以て之を定むべしと云々。……
(大乗院寺社雑事記)

①応仁の乱後も、山城国南部で戦っている畠山政長と畠山義就の両軍への措置

●群雄割拠
　守護大名のなかでも，甲斐の武田氏，駿河・遠江の今川氏，豊後の大友氏，サツ摩・大隅の島津氏などは，みずからの力でひきつづき領国を支配しつづけ，その勢力を隣国にもおよぼしたが，守護大名のほとんどは没落し，国内に新しく台頭した守護代や国人などが勢いをふるった④。このように，実力によって新しい支配体制をきずいた大名を，戦国大名とよぶ。
　駿河の今川氏のもとにいた北条早雲(伊勢長氏)が，小田原を本拠として関東に勢力をのばした。越後では，守護代の長尾景虎が主家上杉氏をついで上杉謙信と名のり，甲斐の武田信玄(晴信)や北条氏と戦った。中部地方では，尾張の守護代織田氏が台頭し，美濃は商人出身の斎藤道三が支配した。
　中国地方では，守護大名の大内氏が16世紀半ばに家臣の陶氏に倒され，その陶氏も安芸の国人毛利元就に倒された。また，東北地方では伊達氏，四国では長宗(曽)我部氏らが勢力を拡大した。いっぽう，畿内周辺では，小勢力の国人同士が戦いつづけ，戦国大名にまで成長するものがなかった。

④九州探題，鎌倉公方，関東管領など，幕府の地方政治の機構も有名無実になった。

〈コラム〉一揆とは何か
　一揆は「揆(方法)をひとつにする」という意味で，そこから，同じ目的のために同盟し行動することをさす言葉となった。
　中世では，当時の常識ではできそうもないことでも，神仏に誓いをたて，掟を定めて一致団結すれば実現可能になると信じられ，社会の各層で一揆が結ばれた。
　とくに室町時代以降は，農民たちが武装して立ち上がった土一揆，そのうち徳政令を要求した徳政一揆，信徒たちが組織した一向一揆や法華一揆，国人が指導した国一揆など，一揆を結んだ蜂起活動がめざましくなった。こうした民衆の同盟意識は，江戸時代にも百姓一揆としてひきつがれた。
　一揆の集団では，神仏に誓い，そむけば罰をうけてもかまわないことを記した起請文２通に全員が署名し，１通を神仏に捧げ，１通を焼いて神水にまぜ，一同がまわし飲みするなどの，結束(一味同心，一味神水)の作法がとられた。

●分国統治
　戦国大名が実力できずきあげた支配領域を分国とよぶ。戦国大名は，富国強兵と領内統治に苦心したが，その政治方針は分国法とよばれる法典によってうかがうことができる。
　分国法には，家臣が私的に同盟を結ぶことや，領地を勝手に売買すること，あるいは分割相続することなどを禁止し，また，喧嘩を両成敗と定める(私闘の禁止)など，家臣を統制するための規定が多く，違反者には厳罰でのぞんだ。
　戦国大名は，国内の国人や地侍を有力な家臣にあずけて統率させ，また，槍や鉄砲による集団戦術の発達とともに，臨時の傭兵にすぎなかった足軽も常備軍に編入するなど，家臣団の組織を拡大，強化していった。
　また，堤防や灌漑用の水路をつくって農業をさかんにし，金・銀の鉱山の開発に力をそそいで，国内の産業の発展につとめた。さらに，国内の道路の整備や関所の撤廃などによって，交通の便をはかり，また，座の特権を廃止した楽市・楽座などの政策によって，商工業を保護した。

〈史料〉
○分国法

一、朝倉館の外、国の中に城郭を構へさせ間敷候。惣別して(すべて)分限あらん者(有力な家臣)は一乗谷へ越され、其の郷、其の村には、代官、百姓等ばかりを置かるべく候事。	（朝倉孝景条々）
一、喧嘩の事、是非に及ばず(理由のいかんによらず)成敗を加ふべし。	（甲州法度之次第）
一、駿遠(駿河と遠江)両国の輩(今川氏の家臣)、或は私として(主君の許可なく)他国より嫁を取り、或は婿に取り、娘をつかはす事、自今以後、これを停止(禁止)しおはんぬ。	（今川仮名目録）

●都市と町衆
　室町・戦国時代には，京都や奈良など古代以来の都市のほかに，各地に都市が発達した。寺社参詣の盛況によって，大寺社の参道周辺に門前町①がおこった。とくに，一向宗のさかんな越前の吉崎，加賀の金沢，摂津の石山(大坂)や河内の富田林などでは，寺院や道場を中心に寺内町が形成され，門徒が集住した。
　戦国時代には，戦国大名の居城を中心として城下町②が多く生まれた。政治の中心となる大名の居城は，戦いに備えていた山城から，交通の便のよい平地にきずいた平城に移った。城下町には，家臣を参勤させ，商人や手工業者も集められて，分国経済圏の中心となった。
　また，水陸交通の発達によって，港町や宿場町などもさかんとなった。港町である堺や博多などでは，町民(町衆)の有力者や商人による自治組織がつくられ，領主から自治の特権を認められていた。これらの町は，周囲を堀で囲み，武士をやといいれて自衛した。
　京都でも，商工業者の町が数町ずつ町組をつくって連合し，町衆たちによって自主的に運営されるようになった。

①伊勢神宮の門前である宇治山田，信濃善光寺の長野など。
②北条氏の小田原，今川氏の府中(静岡市)，朝倉氏の一乗谷，大内氏の山口など。

              </dtext>
            </doc><doc>
              <did>
                JBS-35
              </did>
              <dtitle>
                4　富国強兵への道
              </dtitle>
              <dtext>
                
4　富国強兵への道

●維新の三大改革
　列強に対抗して，国の独立をまもり，近代国家へと転換していくため，新政府は，経済を発展させて国力をつけるとともに，軍備の充実をはかった(富国強兵)。
　新政府が実施した諸改革のなかでも，軍事，租税，教育の改革は，維新の三大改革ともいうべき，国民生活に直接かかわる重要な改革であった。

●徴兵令
　新政府は，これまでの武士にかわって，国民から徴兵した兵士によって近代的な軍隊をつくるため，1873(明治６)年１月，徴兵令を公布し，満20歳に達した男子は，士族，平民にかかわらず３年間の兵役に服させることとした。しかし，多くの兵役免除の規定があり，実際に兵役に服したものの多くは，農民の次三男らであったため，負担の増加をきらって各地で徴兵反対の農民一揆(血税一揆)がおこった。また，特権をうばわれた士族の不満も大きく，士族の反乱につながったが，徴兵を主とする政府軍が勝利をおさめて，近代軍隊が定着した。

〈史料〉
○徴兵告諭
　政府は，1872年に国民皆兵の必要性を述べる徴兵告諭を出した。「血税」を国民の血をとることと誤解された面もあり，徴兵反対一揆が各地で発生した。

……凡ソ天地ノ間一事一物トシテ税アラザルハナシ(税のかからないものはない)、以テ国用(国の必要)ニ充ツ。然ラバ(だから)則チ人タルモノ固ヨリ(本来的に)心力ヲ尽シ国ニ報ゼ(国に奉仕する)ザルベカラズ。西人(西洋人)之ヲ称シテ血税(兵役義務のこと)ト云フ。其生血ヲ以テ国ニ報ズルノ謂ナリ。	(法令全書)

●地租改正
　近代国家の建設をすすめるうえで，財政制度の確立はもっとも重要であった。
　新政府の主要な財源は江戸時代以来の年貢であり，安定した財源の確保をせまられていた政府は，土地制度と税制の改革に着手した。まず1871(明治４)年，田畑の勝手作を認め，翌年には田畑永代売買の禁止をとき，地主と自作農に地券をあたえて，土地の所有権を認めた。
　ついで1873(明治６)年，地租改正条例を定め，1879年までにほぼ全国に地租改正を実施した。その要点は，(1)課税対象を収穫高から地価に変更し，(2)物納を金納にあらため，税率は地価の３％とし，(3)土地所有者を納税者とすることであり，これによって各藩ごとに異なっていた地租は，全国一律に貨幣で徴収される近代的な租税となった。また，地租改正による土地所有権の確立は，資本主義発展の基礎を形づくっていった。
　しかし，政府はこれまでの年貢収入を減らさないことを方針としたので，地主や自作農の税負担はほとんど変わらず，各地で地租改正反対一揆がおきた。なかでも三重県を中心におきた一揆は政府を驚かせ，1877(明治10)年，地租は地価の３％から2.5％に引き下げられた。

〈コラム〉地租改正と地価
　地租率３％は，旧貢租額の確保を目安に設定された。税収は国全体としては確保されたが，地域的にみると，北陸，近畿，山陰，四国，九州では10％程度の軽減となったのに対し，東北，関東，東海，東山などでは５〜10％の負担増となった。いままで軽かった畑への貢租が重くなったことなどがその理由であった。
　明治10年に地租率は引き下げられて農民の負担は軽減されたが，地域的な格差は解消されなかった。のちの帝国議会で，民党が地租軽減とともに，格差是正の地価修正を要求するのは，このためである。

●教育制度
　教育の面では，1871(明治４)年に文部省を新設し，翌1872年に学制を公布した。とくに小学校教育の普及に力がそそがれ，６歳以上の男女すべてが就学することとする国民教育がめざされた。しかし，性急な教育制度は地方の実情にあわず，財政負担も大きかったので，1879(明治12)年には教育令を公布して，義務教育年限を短縮するなど，制度の実際化をはかった。
　高等教育機関としては，昌平坂学問所など旧幕府の施設をうけついで，1877(明治10)年に東京大学を創設したほか，各種の専門学校を設け，多くの外国人教師をまねくとともに，多数の留学生を欧米へ派遣して近代学術の移植につとめた。また，政府が管理する学校とは別に，福沢諭吉の慶応義塾，新島襄の同志社など，独自の教育方針をもつ私立の学校も設立された。
　こうした教育の普及と充実は，日本の近代化をすすめていくうえで大きな役割をはたした。

〈史料〉
○学事奨励に関する被仰出書
　
……自今以後、一般ノ人民華士族農工商及婦女子必ズ邑(村)ニ不学ノ戸(家)ナク、家ニ不学ノ人ナカラシメン事ヲ期ス(めざさねばならない)。人ノ父兄タル者、宜シク此意ヲ体認(よく認めて)シ、其愛育ノ情ヲ厚クシ、其子弟ヲシテ必ズ学ニ従事セシメザルベカラザルモノナリ(学ばせるようにしなければならない)。	(法令全書)

              </dtext>
            </doc><doc>
              <did>
                MS-2
              </did>
              <dtitle>
                調べよう・考えよう2
              </dtitle>
              <dtext>
                
調べよう・考えよう2
資源・エネルギー問題とわたしたちの生き方
▼代替エネルギーの利用
　デンマークでは1980年にはほとんど０％であった風力による発電が，2002年には総発電量の15％以上を占めるようになった。これは石油と石油製品に課税する一方，再生可能なエネルギーによって得られる電力については課税対象から外すなどの優遇措置をした結果であった。今では，デンマークは世界有数の風力発電機生産国となり，各国への輸出もおこなっている。
　このほかにもドイツ，アメリカなどが大量の風力発電をおこなっており，麦畑，牧場，海岸，海上などいたるところにたくさんの風車が整然とならんでいる美しい風景を見ることができる。現在，風力発電は発電設備導入量が急増し，世界で最も急成長しているエネルギー源となっている。
　これに対して，日本の風力発電事業は大きく後れており，総発電量に占めるシェアはごくわずかである。
　2008年現在，風力発電量は200万kWにも届かず，国が決定した2010年度までに300万kWを達成するという目標にはほど遠い状態にある。そして世界で急成長をとげている風力発電機生産の分野でも日本企業の世界に占める割合は低く，国内の風力発電機の多くが輸入製品で占められている。今後，風力発電を世界水準にまで高めるには，電力買い取り制度や事業者への助成制度などの広範な施策が必要とされている。
　なお，山形県庄内町などでは風力発電を町おこしの一環として取り入れており，自然エネルギーを利用したクリーン発電の取り組みは今後も注目される。
資源・エネルギー問題
　現在では，石油が一次エネルギーの中心になり，電力などの二次エネルギーが経済の基盤をなしている。①しかし，石油などの化石燃料や種々の鉱物資源は再生が不可能な枯渇性資源である。また，森林資源などもこのまま大量の消費を続けたならば，その存在量は急速に減少するだろう。地球環境を保全し，次世代に豊かな資源を継承する「持続可能」な経済発展をどのようにして実現するかが，緊急の課題として問われている。
資源・エネルギー対策
【代替エネルギーの開発】　1973年の石油危機以後，各国で，再生が可能な無限エネルギーや，環境汚染物質を排出しないクリーンエネルギーの開発が進められている。
　この種のエネルギーには，太陽光，太陽熱，風力，波力，地熱，潮力，バイオマス②，燃料電池などがある。北欧の国などでは実用化の進んだところもあるが，日本では総エネルギー供給量に占めるこれらの割合は少ない。政府は新エネルギー法③などにより，これらを含む新エネルギーの供給増をめざしているが，経済性や安定供給などの課題もあり，普及のためには補助金政策などを積極的に進める必要がある。
【ライフスタイルの改善】　世界全体のエネルギー消費量は増加の一途をたどり，特に経済成長の著しいアジア地域などではエネルギー需要の急増も予想され，大量消費の社会をさらに拡大させるだろう。
　煌々と輝く深夜の自動販売機，肌寒さを感じる真夏の冷房など，日常生活におけるエネルギーの浪費は枚挙にいとまがない。
　西欧諸国では環境税（炭素税）④による法的措置などもとられているが，わたしたちも自らの生活様式を見直し，身近なところから省エネルギーを実践していかなければならない。
【リサイクル】　わたしたちは毎日一人あたり約１kgのごみを出し，家庭ごみなど一般廃棄物の年間排出量は東京ドームの百数十倍になるといわれている。省資源のためには効果的な廃棄物処理のために三つのＲ「リデュース（減らす），リユース（再使用），リサイクル（再生利用）」に心がけなければならない⑤。
　特にリサイクルについては，日本でも石油危機を契機に，リサイクル運動が高まりをみせ，古紙やアルミ缶の回収，ごみの分別収集などがおこなわれるようになった。2000年には廃棄物対策とリサイクル対策を総合的，計画的に推進する目的で循環型社会形成推進基本法⑥が制定され，これに関連する各種の法律も整備されている。なお，最近ではゼロエミッション（廃棄物ゼロ）に取り組む企業も増えてきている。
【エネルギーの効率的利用】　化石燃料を電気にかえ，それをさらに光や運動にかえると，その過程で大量のエネルギーが放出される。このようなむだをなくすためには，エネルギーの効率的利用技術とそのシステム化が必要である。
　最近では，節電型の電気製品，ハイブリッドカーや低燃費の自動車などが開発され，これらを推進するための法的規制や税制上の優遇措置なども実施されている。また，発電とともに，蒸気や熱などを同時に利用するコジェネレーション（熱電併給）も注目されている。これはエネルギーの利用効率がすこぶる高く，日本でもホテル，病院などつねに熱供給を必要とする所で利用されるようになってきた。
日本の原子力発電
　原子力は，大量のエネルギーを供給でき，温室効果の影響も少ないといわれる反面，人体に有害な放射線を大量に発生させるため，その安全性が問題になる。1979年のアメリカのスリーマイル島，1986年のソ連（現在のウクライナ）のチェルノブイリ発電所の事故を契機に，オーストリアでは完成したまま使われずに封鎖されていた原子力発電所が解体され，スウェーデンでは国民投票で原子力発電所の全廃が決められた⑦。
　日本では，プルトニウムを燃料とする核燃料サイクルの開発を基本政策としてきたが，1995年の高速増殖炉⑧「もんじゅ」の事故以来その方針を疑問視する意見もみられるようになった。また，茨城県東海村などでの臨界⑨事故や，地震による原子力発電所の破損などがあり，原子力施設の管理のあり方が問われている。このようななかでの，新たな原子力発電所の建設や，プルサーマル計画⑩などは，原子力のメリット，デメリットを考慮したうえで，慎重に計画を進めることが望まれる。
①石炭，石油，天然ガス，水力，原子力などエネルギー源から加工をへずに直接に得られるものを一次エネルギーといい，電力，都市ガスなど一次エネルギーから形態を変化させて得られるものを二次エネルギーという。
②生物エネルギーのこと。家畜のふん尿から出るメタンガスや，可燃ごみを利用するなど有機物をエネルギー源とする。
③石油，石炭，天然ガスなどの化石燃料や原子力など旧来型のエネルギー以外のエネルギーの総称。
④環境税は，環境悪化の原因となるものに税を課し，その排出や消費を抑制する。化石燃料の消費を減らすための炭素税はその代表例。
⑤refuse（断る）を入れて四つのRの取り組みが主張される場合もある。
⑥大量廃棄の社会を資源循環型の社会に変えるために，天然資源の消費の抑制，廃棄物の減量と再資源化などを優先する基本姿勢が示されている。
⑦2009年に政策転換がはかられ，2010年に既存の原子炉建て替えを認める法律が成立した。
⑧原子力発電の燃料としてプルトニウムを利用し，それを再生産してさらに利用することが期待されている。しかし，ナトリウム漏れ事故を起こすなどの危険性が高く，欧米では開発を断念する国があいついだ。
⑨核分裂の連鎖反応が続く状態を臨界という。
⑩原子力発電所の使用済み燃料から取り出したプルトニウムとウランを混合して新たに燃料として利用する計画。


              </dtext>
            </doc><doc>
              <did>
                MS-12
              </did>
              <dtitle>
                〈３〉生きがいと進路の創造
              </dtitle>
              <dtext>
                
〈３〉生きがいと進路の創造
キャリアの開発
　青年期には，将来の職業生活に役立つような知識や技能を身につけることが要求される。しかし今日では，目先の進学先や就職先を選ぶことよりも，将来にわたる自分の生き方を考えながら人生を設計するキャリア開発の考え方が必要になってきている。
　キャリアとは，職業生活を中心としたその人の経歴全体のことである。どこの会社に勤めていて，どのような役職にいるかというようなことではない。職業生活を支える余暇の過ごし方や趣味も含まれるし，また家事・育児をはじめとする家庭生活も，就業以前の学校生活も，退職後の生活も，すべてがキャリアに含まれる。むしろ，その全体がキャリアなのである。キャリアを開発することは，自分自身の「生きがい」をどのようにつくりあげていくかということにほかならない。
職業を選ぶ
　職業についていえば，学歴重視や年功序列・終身雇用の風潮が崩れてきたことは，選択の幅を広げたようにみえる。しかし，その分だけ従来以上に自分の将来の見通しをたて，自分をどう向上させていくかを意欲的に考えなければならなくなっている。
　わたしたちはよく「自分に合った仕事がしたい」という。これは，自分自身の興味・適性・能力と，さまざまな職業についての情報をつきあわせ，両者の適合性を確かめるという考え方である。学校でしばしばおこなわれる職業に関する適性検査などは，それを明らかにするための情報を与えてくれるが，検査で得られるのはあくまで一つの情報にすぎず，それで自分の適性をすべて明確にすることはできない。
　むしろ大切なのは，経験と学習によって，興味・適性・能力は変わってくるということである。つまり，どれだけ広く職業について調べ，どれだけ自らの能力を向上させていくかという，自分自身の積極的な取り組みが必要だということである。それによって，最初は考えてもみなかった分野で成功したり，無理に思えていた希望や夢を実現に導いた人々も多い。興味・適性・能力は，広げたり高めたり伸ばしたりできるものであり，キャリアは大きく変わる可能性がある。
多様な生きがいの追求
　キャリアが家庭生活も退職後の生活もすべて含めた総体であるならば，職場での仕事はもちろん，家事や育児，介護などにおける自分の役割も，明確にしていく必要がある。男女雇用機会均等法・男女共同参画社会基本法や，育児休暇・介護休暇などの制度的な充実は，わたしたちに新しいキャリア開発の機会を与えた。これらの法や制度を，自分たちの生き方に，どう具体的に反映させていくかを考えなければならないときがきている。社会文化的につくりあげられた性差であるジェンダーを固定的なものとしてとらえることなく，幅広いキャリア開発をめざすようにしたい。さらに，労働時間の短縮や長寿化によって，地域社会への参加と奉仕などをはじめとする多様な人間関係の広がりが重要さを増してきている。こうしたさまざまな面から，「生きがい」を見つけるというよりも「生きがい」を積極的に創造することが求められている。

              </dtext>
            </doc><doc>
              <did>
                PE-25
              </did>
              <dtitle>
                （1）経済主体と経済の循環
              </dtitle>
              <dtext>
                
第2節　現代経済のしくみ

（1）経済主体と経済の循環

Ａ　家計はどのような経済活動を行っているか。
Ｂ　企業の経済活動はどのように多様化しているか。
Ｃ　政府は経済循環の中で，家計や企業とどうかかわっているか。

●経済主体
　家計，企業，政府はそれぞれ目的も経済活動の内容も異なっているが，どこからか収入を得てそれを所定の目的を達成するために支出している点では同じである。このように収入と支出の経済活動を行う主体を経済主体といい，現代では家計や企業などの民間部門だけでなく，政府（公的部門）も公共的な目的のために重要な経済活動を行っている。また最近では，非営利団体としてのNPOやNGOも経済活動の重要な担い手となりつつある。

●家計の活動
　家計は賃金，利子，配当などの形で所得を得て，所得の中から家庭を維持し，家族の暮らしを向上させるために消費支出を行っている。食料や衣料などの消費財への支出だけでなく，レジャーや教育などへの支出も経済統計上は消費支出と見なされる。消費は所得が増えると増加し，国全体の消費支出は好景気の時期には大幅に増加する傾向にある。消費はまた，家計が保有している株や土地などの価格が上昇すると増加する傾向がある。これを資産効果といい，株価や地価が急上昇したバブル経済期には資産効果が働いて消費が大幅に増え，バブル崩壊後には逆の効果（逆資産効果）が働いて消費が減退した。
　所得から消費支出を差し引いた残りは貯蓄とよばれる。金融機関への預貯金だけでなく，株式，国債，社債などの証券類の購入，あるいは生命保険料の支払いなども貯蓄となる。

●企業の活動
　個人企業にしろ法人企業にしろ，利潤をできる限り大きくすることが企業の主たる目的である。なかには市場占有率①（マーケット・シェア）や売上高を高めることに主眼をおいている企業もあるが，これらの目的も利潤追求の一つのあらわれである。
　利潤とは，一定の会計期間における製品の売上高から，その期間に発生したさまざまな費用を差し引いた残額である。費用には原料費や材料費，賃金などの人件費のほか，広告・宣伝費，借入金に対する利子支払い，設備を更新するためにとっておかれる減価償却費②なども含まれる。

①市場占有率　一企業の製品がその産業の市場全体に占める割合。100％であれば独占となる。
②減価償却費　企業会計上の費用としてとらえたものを減価償却費といい，国民所得の計算では，固定資本減耗（→p.118）という。

　設備投資は生産と並ぶ企業の重要な活動である。企業は設備投資の活動によって企業活動を量的に拡大するだけでなく，新たな技術を導入したり，研究開発（R＆D）によって自ら新技術を開発することによって質的にも変化していく。生産のエレクトロニクス化にともなって生産工程にロボットなどを導入したり，OA化の進展にともなって事務部門にコンピューターその他の情報機器を導入するなど，新技術・情報関連投資が設備投資の中でも大きな比重を占めるようになってきた。
　産業構造の転換が進んでいる現在，企業もまた自らの構造転換を迫られている。例えば，従来の企業の一部門を独立させて別会社にしたり，反対に事業の多角化をはかって他の産業分野に乗り出すなど，リストラクチャリング（事業内容の再構築）を行っている企業がたくさんある。情報化の進展にともなって情報処理を専門会社に外注（アウトソーシング）したり，情報処理ソフトを他企業と共有するケースも多く見られるようになった。これもリストラクチャリングの一環である。さらに大企業の中には多国籍化をはかったり外国企業を買収するなど，積極的に国際事業戦略を推進しているところも多い。
─────
企業の社会的責任　バブル経済のころには，企業は芸術・文化の支援活動（メセナ）や福祉などに対する慈善活動（フィランソロピー）をさかんに行った。しかしこれらは資金提供が中心であったために，バブルが崩壊すると，活動も先細りになっていった。最近では，企業活動の広がりとともに，利潤追求だけではなく，環境保護①や法令・社会的規範の遵守（コンプライアンス）など企業の社会的責任（CSR）が世界的に重視されるようになってきている。
─────

①環境保護　企業の中には国際標準化機構（ISO）による14000シリーズ（環境保全）の認証の取得を目指すものもある。

●経済活動の循環
　企業の生産活動は一回限りの活動ではなく，毎年繰り返して行われる。このことは裏を返すと，生産物に対する家計の需要が，ということはまた家計の所得が，とぎれることなく生み出されるということである。家計の所得は，家計が企業に労働力を販売した見返りとして，賃金という形で生み出される。家計と企業のあいだでは，生産物の売買と労働力の売買という二重の売買が行われ，この二重の売買によって持続的な生産が可能になる。
　売買活動は企業と政府，家計と政府のあいだにおいても行われる。政府は公共事業を行う際に必要な資材を企業から購入し，その対価を企業に支払う。また，家計は政府に公務員として労働力を提供し，その対価として給与を受け取る。いっぽう，政府はこのような支出をまかなうために，家計や企業から税金を徴収する。こうして市場経済では三つの経済主体のあいだで双方向的な売買活動が行われ，この活動を通じて，生産→分配（所得の発生）→消費→生産→……というふうに，経済が循環し再生産されていく。

              </dtext>
            </doc><doc>
              <did>
                JB-46
              </did>
              <dtitle>
                3　維新政権の成立
              </dtitle>
              <dtext>
                
3　維新政権の成立

●幕府の倒壊
　将軍となった徳川慶喜は，大規模な陸海軍の改革を行い，またフランス公使ロッシュの意見を容れ，人材登用と職制改革をすすめた(慶応の改革①)。
　幕府が体制を補強する一方で，国内での対立は深まった。土佐藩の山内豊信(容堂)は，後藤象二郎らの建策を容れ，政権を朝廷に統一して合議政治を行う新たな国家構想(公議政体論)を押し立て，朝廷へ大政を奉還するよう慶喜に進言した②。サッ長は武力討幕をくわだて，1867(慶応3)年10月14日，岩倉具視らの工作によって討幕の密勅を獲得するが，徳川慶喜は自ら大政奉還を奏上して，岩倉らの動きを封じた。慶喜は朝廷を頂点とした政権の中核に徳川家が据わることを構想したのである。
　しかし12月9日，討幕派はサッ長の兵力を京都周辺に集結させ，まだ若い明治天皇を戴き，王政復古を宣言した(王政復古の大号令)。幕府とともに摂政・関白などの旧制度が廃止され，総裁・議定・参与の三職がおかれた。さらに小御所会議において徳川慶喜に官位と領知の返上(辞官納地)を求めることが決められた。いわゆる王政復古のクーデターである。

①フランス(陸軍)やイギリス(海軍)から軍事顧問団が招聘され，旗本軍制を洋式化した。また横須賀製鉄所(造船所)，江戸の関口の銃砲製作所や滝野川反射炉の建設が着手された。
②土佐藩郷士出身の坂本竜馬は後藤に「船中八策」を示し，上下議政局設置など新たな国家構想を示した。

〈史料〉
王政復古の詔
徳川内府①、従前御委任の大政返上、将軍職辞退の両条、今般断然聞し食され候。抑癸丑②以来未曾有の国難、先帝③頻年④宸襟
⑤を悩ませられ候御次第、衆庶⑥の知る所に候。之に依り叡慮を決せられ、王政復古、国威挽回の御基立てさせられ候間、自今、摂関・幕府等廃絶、即今先仮に総裁・議定・参与の三職を置かれ、万機行はせらる可し。諸事神武創業の始に原き、縉紳⑦・武弁⑧・堂上⑨・地下⑩の別なく、至当の公議を竭し、天下と休戚⑪を同じく遊ばさる可き叡慮に付き、各勉励、旧来驕惰⑫の汚習を洗ひ、尽忠報国の誠を以て奉公致すべく候事。……
（法令全書）
　①慶喜。内大臣であった　②一八五三（嘉永六）年　③孝明天皇　　④毎年　⑤天皇のみこころ
　⑥一般人民　⑦公ギョウ　⑧武家　⑨貴族　⑩庶民　⑪喜びと悲しみ　⑫おごり怠る

●戊辰戦争
　12月末，旧幕府側は江戸のサツ摩藩邸を焼き討ちし，大坂城の慶喜は旧幕府軍に京都進撃を命じた。1月3日，サッ長軍と旧幕府軍は鳥羽・伏見の戦いで激突し，数の上では優っていた旧幕府軍が敗退した。慶喜は形勢不利とみて江戸で恭順謹慎の意を示した。
　新政権は慶喜追討令を発し，西日本の諸藩を従えると，江戸へ向けて東征軍を発した。これには新政に期待する草莽隊も多く参加し，人心掌握のために旧幕領の年貢半減も布達されたが，諸大名の帰順がすすむと密かに撤回された。東山道軍に加わった赤報隊は，それを知らずに年貢半減を鼓吹したため，偽官軍とされ，隊長相楽総三は処刑された。
　世直し一揆や都市での打ちこわしが続発する中で，1867年の半ばから翌年春にかけて，東海から西日本を中心にええじゃないかの民衆乱舞が広がった。
　新政権は欧米列強に承認を求め，各国がいち早く中立の立場をとった点も新政権に有利にはたらいた①。1868(慶応4)年4月11日，江戸城は明け渡され，慶喜は水戸へ隠遁したが，強硬派の旧幕府軍は関東各地で抗戦した。新政府軍は5月15日，上野の彰義隊を掃討し(上野戦争)，徳川氏を駿府70万石に移すこととした。東北では旧幕側の会津・庄内両藩の追討が命じられたが，両藩に同調した東北諸藩は奥羽越列藩同盟を結んで新政府に対抗した(東北戦争)。この戦争は会津・庄内が降伏する9月まで続き，さらに戦場を箱館へ移した。榎本武揚は旧幕府の軍艦を率いて蝦夷地を占拠し，1869年5月まで箱館を拠点に新政府に抵抗した(箱館戦争)。この一連の内戦を戊辰戦争という。

①新政権は，神戸事件(岡山藩兵と外国兵が衝突した事件)，堺事件(土佐藩兵が仏軍水夫を殺害)，イギリス公使パークス襲撃事件などを列強の意向に沿って処理して信頼を得て，列強の支持を引き出している。

●維新政権の成立
　1868(慶応4)年3月，新政府(維新政権)は五箇条の誓文を発布し，天皇親政と開国進取をめざす政権の基本方針を明らかにした。諸大名・旧幕臣はこぞってこの誓文に署名し，新政権に忠誠を誓った。つづいて閏4月には政体書が公布され，太政官政府の官制と府・藩・県の地方制度が定まった②。政体書では議政官(立法)・行政官(行政)・刑法官(司法)の三権分立のたてまえがとられ，議政官は議定と参与からなる上局と府藩県から出る貢士からなる下局で構成された。下局は1869年に公議所(のち集議院)となり，諸藩から公議人が派遣されて議論を交わした。
　1868(明治元)年7月，江戸を東京と改め，9月には明治に改元するとともに一世一元の制が採用された。翌1869(明治2)年2月，明治天皇は太政官政府とともに東京へ移った(東京遷都)。6月には，新政府は版籍奉還を命じ，諸大名はあらためて天皇から知藩事に任命され家禄を支給された。旧幕府から接収した地域(府・県)は直轄化されたが，諸藩はいぜんとして大名家が支配し，諸藩の意見を吸い上げて公議世論を尊重する姿勢を貫こうとすると，統一的な政策の実施はおぼつかなかった。
　新政府は民衆に対しては五榜の掲示を示し，キリシタン禁令などの旧慣継続を宣言し，隠れキリシタンの大弾圧を行った(浦上教徒事件)③。また，祭政一致の方針下に神ギ官を設立し，神仏分離令を発布して神道の国教化をはかろうとした。このため，各地で寺院や仏像を破壊する廃仏毀釈の動きが広まった。1870(明治3)年には大教宣布の詔が出され，神道の国教化が推進されたが，実効性は少なかった④。

②この制度を府藩県三治制という。府県は接収された幕領におかれ，そのうち直轄都市は府となったが，すぐに江戸・大坂・京都三府のみとなる。
③1867年，公然と活動をはじめた浦上(長崎近郊)の信者が弾圧され，さらに明治に入ると村ぐるみ3200人を超える信徒を各地へ配流する事件となった。
④1872(明治5)年には教部省が設置され，神仏合同での教化運動を展開した。

〈史料〉
五箇条の誓文
一、広ク会議ヲ興シ、万機①公論ニ決スベシ
一、上下心ヲ一ニシテ、盛ニ経綸②ヲ行フベシ
一、官武一途庶民ニ至ル迄、各其志ヲ遂ゲ、人心ヲシテ倦マザラシメンコトヲ要ス
一、旧来ノ陋習③ヲ破リ、天地ノ公道ニ基クベシ
一、知識ヲ世界ニ求メ、大ニ皇基ヲ振起スベシ
　①もろもろの政治　②国をおさめ、民を救う方策　③悪い習慣。ここでは攘夷をさしている

●廃藩置県
　欧米列強に対抗しうる近代的中央集権国家づくりこそが新政府の課題であったが，現実の新政府が成り立つ基盤はきわめて脆弱なものだった。
　戊辰戦争の戦費は太政官札を大量発行(4800万両)することによって調達したが，直轄地からの年貢収入のみでは収支をまかなうことはできず，藩収入の一部を上納させた①。
　1868(明治元)年，新政府と諸藩が財政難から年貢増徴策をとったこともあり，全国で大規模な一揆が続発した。69年には，戦後の処遇をめぐって長州藩の諸隊反乱(脱隊騒動)がおこり，開国方針への転換に憤ったかつての尊攘派の要人襲撃事件もあいついだ②。新政府はこのような尊攘派の反政府活動と全国で激発する一揆との結合を最も恐れていた。版籍奉還ののち，中小の諸藩の中には厳しい財政難から廃藩を願うものもあり，また新政府内部には中央集権体制をめざす郡県論を主張するものも多かった。こうした背景のもと，1871(明治4)年，サッ長土三藩の兵士1万人余が上京し親兵に取り立てられた。7月，サッ長の大久保利通・木戸孝允らが中心となり，廃藩置県の詔によっておよそ260ある藩を廃止し，事態の打開を図ろうとした。
　廃藩置県の断行により封建的領有制が一掃され，軍事と財政の権限は中央政府に集中した。政府には正院・右院・左院と，外務・大蔵・工部・兵部・司法・文部・神ギ・宮内の8省がおかれ，府知事や県令(のち県知事)などの地方長官は中央から任命された。知藩事の地位を追われた諸大名の多くは東京へ出て華族としての生活を保障された。後に県は統廃合されて3府72県の地方制度となった。

①直属軍創出では，1871年，全国一律に万石5人の徴兵差出(辛未徴兵)を命じたが，はかばかしい成果は得られなかった。
②参与横井小楠に続き，国民徴兵制度を主張した兵部大輔大村益次郎が秋に暗殺され，1871年には参議広沢真臣が暗殺された。

●岩倉遣欧使節団
　廃藩置県によって中央集権を実現した新政府は，1871(明治4)年7月，清国と日清修好条規を締結した。これは，最恵国待遇がなく，領事裁判権の相互承認を特色とした対等条約であった。
　新政府は，欧米諸国とも対等の外交を行うことを目指し，同年，右大臣岩倉具視を特命全権大使とし，副使には参議木戸孝允のほか大久保利通，伊藤博文，山口尚芳など要人がならぶ大規模な使節団を編成した③。この岩倉使節団は，参議西郷隆盛や板垣退助らに委ねた留守政府に対し，新規の政策や官僚の補充を行わないことを約束させて，11月欧米へ出発した。使節団の目的は不平等条約改正の予備交渉にあったが，それは最初の訪問国アメリカで早くも挫折した。しかし1年10か月に及んだ視察調査は，欧米の進んだ文明や政治・経済・軍事・教育などの諸制度を直接に見聞し，日本の近代化の方法を探るうえで大きな成果となった。

③使節団は，随員を含めて約50名で構成され，それに金子堅太郎，中江兆民，津田梅子ら49名の留学生が同行した。

              </dtext>
            </doc><doc>
              <did>
                JB-5
              </did>
              <dtitle>
                3　大和王権の形成と古墳文化
              </dtitle>
              <dtext>
                
3　大和王権の形成と古墳文化

●前方後円墳の登場
　3世紀の半ばをすぎると，纏向遺跡に隣接する箸墓古墳に代表されるように，瀬戸内・近畿地方を中心に前方後円墳がつくられるようになる。後円部に首長の遺体を埋葬し，前方部で祭祀を行った前方後円墳は，首長の力の大きさを誇るとともに，新しい首長が支配者としての宗教的権威を受け継ぐための施設であった。その築造技術や副葬品が画一的であり，特に大きな古墳が近畿地方にあるため，瀬戸内・近畿地方の首長たちの連合が生まれており，畿内地方の首長がその盟主の地位にあったと考えられる。
　古墳は，その形態によって，前方後円墳・前方後方墳・円墳・方墳などがあるが，前方後円墳は当時の政治的つながりを理解するうえでとくに重要である。前方後円墳に代表される古墳がつくられた時代を古墳時代とよび，前期(〜4世紀)，中期(5世紀)，後期(6世紀)に分けている③。
　前方後円墳は，前期のうちに九州から東北地方南部まで広がった。古墳の墳丘は，葺石や埴輪で飾られた。埴輪は，弥生時代の特殊器台・特殊壺の流れをくみ，はじめは円筒形のものが主であったが，のちには家・動物・人物などをかたどった形象埴輪も用いられた。中期までの古墳の埋葬施設は，木棺や石棺を竪穴式石室や粘土槨におさめたものであり，棺には鏡をはじめとするたくさんの品々が副葬された。前期の副葬品は，銅鏡や鍬形石，勾玉など呪術的・宗教的色彩が強く，被葬者が司祭者的性格をもっていたことがわかる。このほか鉄製農具なども副葬されたが，中期以降には，武器・武具・馬具の副葬が増え，被葬者が軍事指揮官的性格を強めたことを示している。

③飛鳥文化の時代とされる7世紀以降も古墳がつくられているので，この時期を古墳時代の終末期とよぶこともある。

●大和王権の成立
　各地につくられた前方後円墳の中には，大和地方のものと相似形のものもあり，築造技術などが大和地方から伝えられたことを示している。また，同じ鋳型などからつくられた三角縁神獣鏡などの鏡も各地の古墳から出土しており，これらも政治的なつながりを示している。日本列島の広い範囲の首長たちは，大和地方の勢力を中心にして政治的なつながりをもつことになり，築造を許された古墳の形態や規模によって，序列化されることになった。その中心に位置する大和地方の政治権力を大和王権(倭王権)とよんでいる①。
　中期には，前方後円墳のつくられる地域はさらに広がった。奈良盆地のウワナベ古墳や大阪平野の大山古墳(伝仁徳天皇陵)・誉田山古墳(伝応神天皇陵)のような巨大な前方後円墳がつくられた。これは，法円坂遺跡のような近畿地方につくられた巨大な倉庫群の存在とともに，大和王権の力の大きさを物語っている。このような大和王権の盟主は大王とよばれている。
　また，女狭穂塚，造山古墳・作山古墳・太田天神山古墳など日向・吉備・毛野地方にも大きな古墳がつくられており，各地の首長は大和王権と政治的に結びつつも，それぞれの地域で独自の勢力をほこっていた。三ツ寺Ⅰ遺跡は，祭祀遺構や倉庫跡などを含む巨大な豪族居館跡であり，当時の地方豪族の地域支配の拠点と考えられる。
　471年に記されたとされる稲荷山古墳から出土した鉄剣には「ヲワケ臣」が，江田船山古墳から出土した鉄刀には「ムリテ」が，「ワカタケル大王」に仕えていたと刻まれている。ワカタケル大王は『古事記』『日本書紀』にみえる雄略天皇とされ，地方豪族を大王のもとに出仕させていたことがわかる①。

①中国の唐の時代にいたるまで，「倭(倭国)」は国際的に認知された名称であった。国内的には，倭をヤマトとよむようになった。
①『古事記』『日本書紀』では，大王は「天皇」と表記されている。「天皇」号は7世紀後半に成立したものであり，天皇の名を漢字2文字で表すことは，8世紀半ばにはじめられた。

●古墳文化の展開
　古墳時代の首長たちは，しだいに集落の外に自らの居館を営んだ。首長の支配下にある人々は，数棟の竪穴住居や平地住居と井戸や倉庫からなる溝や柵で区画された屋敷地に住むようになり，これがいくつか集まって集落が営まれたが，集落に環濠をめぐらすことはまれになった。土器では弥生土器の系譜を引く土師器が用いられた。
　中期になると，戦乱をのがれて朝鮮半島から渡来した人々が，新しい文化をもたらした。5世紀には登り窯などを用いて焼成する硬質で灰色の須恵器という土器がつくられるようになった。また，竪穴住居のなかにカマドをつくって，煮炊きを行うようになり，米を蒸すための甑という土器が用いられるようになった。馬と馬具がもたらされ，乗馬の風習も急速に広まっていった。このほか，金属加工の技術や進んだ織物の技術なども伝わった。
　このような先進技術は，鉄資源の入手経路などとともに，朝鮮半島や中国大陸との交流を掌握し，渡来人を配下においた大和王権によって独占されており，これによって，大王は地方豪族に対する優位を維持した。
　鉄を用いた農具が普及し，水稲耕作が進展するにともない，農耕に関わる祭祀も整えられていった。春には豊作を祈る祈年祭が，秋には収穫を神に感謝する新嘗祭が行われた。首長には，祖先の霊を引き継ぎ，神を祀ることが期待された。秀麗な山，巨石，神聖な樹などが神の宿るところとされ，これに供え物をしたり祭りを行うために，社がつくられていった。また災いからのがれるための禊や祓，骨を焼いて吉凶を占う太占の法，熱湯に手を入れて真偽の判定を行う盟神探湯などの呪術的風習も行われた②。

②玄界灘に浮かぶ沖ノ島(福岡県)では，4世紀以降海上交通の安全を祈る国家的祭祀が行われた。大神神社(奈良県桜井市)は，三輪山そのものを神体としており，大国主命を祀る出雲大社(島根県大社町)の建物は，古い様式を伝えているとされている。

              </dtext>
            </doc><doc>
              <did>
                JB-34
              </did>
              <dtitle>
                2　キリスト教禁止と鎖国
              </dtitle>
              <dtext>
                
2　キリスト教禁止と鎖国

●東アジア諸国との関係改善
　家康は，秀吉の強圧的な外交政策を改め，明や朝鮮との国交回復をはかるとともに，東南アジア諸国との和親につとめた。ルソン・安南・カンボジア・シャムなどには親書を送り，朱印状を携行した船の保護と貿易の許可を求めた。この場合の朱印状とは，渡航許可書で，島津家久，有馬晴信，松浦鎮信などの九州諸大名，京都の角倉了以，茶屋又四郎(三代目四郎次郎)，摂津の末吉孫左衛門，堺の今井宗薫，博多の島井宗室，長崎の末次平蔵などの商人に与えられた。朱印船貿易によって輸出されたものは銀・銅・鉄・硫黄などの鉱産物や工芸品など，輸入品は中国の生糸・絹織物，南方産の象牙・鹿皮・鮫皮・砂糖などであった。
　貿易がさかんになると，海外に移住する日本人も増え，東南アジア各地に日本町②ができ，自治が認められた。なかには，シャムの王室に重く用いられた山田長政のような者もでた。
　一方，長崎には，マカオを根拠としたポルトガル人が秀吉の時代から続けて来航していた。ポルトガル商人は，日本において必需品であった中国産の生糸(白糸)をもたらして大きな利益をあげていたが，1604(慶長9)年，幕府は特定商人(糸割符仲間)に生糸を一括購入させる糸割符制度③をもうけ，安値で生糸を輸入しようとした。
　日本と朝鮮との講和は，対馬藩主の宗氏の努力によって実現し，1607(慶長12)年には朝鮮の使節が来日した。ついで1609(慶長14)年，宗氏は，釜山に設けられた倭館に，毎年20隻の船を派遣し，貿易することを認められた(己酉約条)。明との国交は回復しなかったが，幕府が中国の商船を歓迎したことから，長崎や平戸に来航する中国船(唐船)は多かった。また，東南アジアの各地で，日本と明の商人が取引する出会貿易もさかんに行われた。
　しかし，家康が行った外交政策には，琉球の征服のように強圧的なものもあった。15世紀以来，琉球では尚氏が王国を建てていた。秀吉は，琉球と友好関係をたもっていたサツ摩の島津氏を通じて琉球の服属と朝貢を求め，朝鮮出兵に際しては兵糧の調達を命じた。徳川幕府の成立後，島津氏は，琉球との独占的な貿易関係を維持するため，1609(慶長14)年，幕府の許可を得て琉球に侵攻した。敗北した琉球は，王国こそ維持したものの，実質的にはサツ摩藩の支配下におかれた(琉球征服)。しかし，琉球は中国(明・清)から冊封を受けていたので，日中両国に両属する複雑な関係におかれることになった。

②日本町は，交趾国(ベトナム中部)のツーランとフェフォ，カンボジアのプノンペンとピニヤルー，シャム国(タイ)のアユタヤ，フィリピンのマニラ近郊のディラオとサンミゲルなどに建設された。
③糸割符制度は，当初輸入量の多いポルトガル貿易に対するものだったが，のちにオランダ貿易にも適用された。

●ヨーロッパ諸国との貿易
　関ヶ原の戦いのあった1600(慶長5)年，豊後にオランダ船リーフデ号が漂着した。貿易振興をはかっていた家康は，船員のヤン・ヨーステンとウイリアム・アダムズ(三浦按針)を江戸に招き，外交・貿易の顧問とした。このころヨーロッパでは，スペインから独立したオランダと毛織物工業のさかんなイギリスが台頭し，国家の保護のもとでそれぞれ東インド会社を設立し，アジア貿易に進出していた。1609(慶長14)年，オランダ船が来航し，家康から貿易を許されて平戸(長崎県)に商館を開き，1613(慶長18)年にはイギリス船が来航し，同様に平戸に商館を開いて日本との貿易を開始した。
　また家康は，ルソンを根拠地としたスペインとの貿易をめざし①，1610(慶長15)年には，京都の商人田中勝介をスペイン領のノビスパン(今のメキシコ)に派遣した。仙台の伊達政宗も，家臣支倉常長をメキシコ経由でスペインやローマに派遣した(慶長遣欧使節)。しかし，これらの通商は実現しなかった。

①家康は，スペイン船の浦賀(神奈川県横須賀市)寄港を許すことをルソン総督に伝えた。

●禁教と貿易統制の強化
　家康は，貿易の利益のため，キリスト教宣教師の渡来と布教を黙認していた。そのためキリスト教は各地に広まり，信者は激増した。宣教師の本国への報告によると，1605年ごろ，信者の数は70万人に達し，京都・大坂・堺などの主要都市には教会堂が建てられた。
　オランダ，イギリス②の新教国は，貿易のみで布教を行わなかったが，旧教国のスペイン，ポルトガルはさかんに布教を行った。家康は，布教がスペイン，ポルトガルの他国侵略に深く関わっており，信者の増大に不安を感じたことから，1612(慶長17)年直轄領に禁教令を出した。翌年にはそれを全国に広げて信者に改宗を迫り，教会堂を破壊し，宣教師らを国外に追放した③。
　家康の後を継いだ秀忠も，禁教の方針をとり，貿易統制を進める必要から，1616(元和2)年には，ヨーロッパ船の寄港地を平戸と長崎に限定し，朱印状の発行を制限するようになった。1623年(元和9)年，イギリスは，貿易の実績があがらないことから，平戸の商館を閉鎖して日本から撤退した。1624(寛永元)年には，布教をやめようとしないスペイン船の来航を禁じた。その後，トンキン(現在のベトナム)で朱印船が焼き討ちされたため，将軍権威が損なわれることを恐れた幕府は朱印状の発行をますます限定するとともに，1631(寛永8)年には朱印状のほかに老中の発行する奉書による許可を義務づけた(奉書船貿易)。
　秀忠の死後，家光は，禁教と貿易統制のいっそうの強化をはかった。1633(寛永10)年，奉書船以外の日本船の海外渡航を禁止し，諸大名には信者の捕縛などを命じ，1635(寛永12)年には，日本人の海外渡航をいっさい禁じるとともに，在外日本人の帰国も禁止し，中国船の寄港地も長崎に限定した。ついで翌年，新しく築造した長崎の出島にポルトガル人を移して禁教を徹底するとともに，ヨーロッパ人と日本人の間に生まれた子を国外に追放した。

②オランダ人・イギリス人は，紅毛人とよばれた。
③1614(慶長19)年には，もと大名であった高山右近ら300人をマカオやマニラへ追放し，1622(元和8)年には，有力宣教師や信者ら55人を長崎で処刑した(元和の大殉教)。

●島原の乱と沿岸防備体制の構築
　九州の島原(長崎県)，天草(熊本県)地方は，キリシタン大名有馬晴信，小西行長の旧領で，キリスト教の信者が多かった。幕府の厳しい迫害と領主松倉重政の圧政のため，この地方の土豪，農民，漁民たちは，1637(寛永14)年10月，益田(天草)四郎時貞という16歳の少年を総大将として一揆をおこした。これを島原の乱(天草・島原の一揆)という。一揆勢は，有馬，小西両氏の旧家臣の指導のもとに，有馬地方の原城跡にたてこもった。幕府は，九州諸藩を中心に12万人あまりの軍勢を動員し，翌年2月，ようやく鎮圧した。幕府は，島原の乱に衝撃を受け，キリスト教信者を根絶させるため，1639(寛永16)年，ポルトガル船の来航を禁止した。翌40(寛永17)年には，貿易再開の嘆願に来たマカオからの使節を処刑し，ポルトガルやその同盟国であったスペインの報復攻撃や宣教師の潜入を阻止するため，九州大名を中心に遠見番所の建設，長崎の警備，沿岸の防備を命じた。そして，1641(寛永18)年，平戸にあったオランダ商館を長崎の出島に移すことによって，外国との関係は幕府の完全な統制下におかれることになった。
　幕府は，キリスト教徒を根絶するため宗門改めを行い，すべての人々をどこかの寺の檀家とし，町や村ごとに宗門人別改帳(宗門人別帳)をつくらせ(寺請制度)，とくに信者の多かった九州北部では絵踏を行わせた①。また，キリスト教徒本人やその親類縁者を監視する類族改めを行った。宗門人別改帳は戸籍の役割ももち，移転や結婚，旅行などにも寺の発行する寺請証文が必要とされた。

①絵踏は，のちに毎年正月に行われるようになった。

〈史料〉
寛永十六年令①
一、日本国御制禁成され候切支丹宗門の儀、其の趣を存じながら彼の宗を弘むるの者、今に密々差し渡②すの事。
一、宗門の族、徒党を結び邪儀を企つれば③、すなはち御誅罰の事。
右これにより自今以後、かれうた④渡海の儀、これを停止せられをはんぬ。此の上若し差し渡すにおゐては、其の船を破却し、ならびに乗り来たる者速かに斬⑤に処せらるべき旨、仰せ出ださるる所なり。	（徳川禁令考）
　①一六三九年七月五日　②密航してくる　③違法をくわだてる（島原の乱をさしている）
　④ポルトガル船　⑤斬罪のこと

●鎖国下の貿易
　日本は当時ポルトガルとの貿易が大きな比重を占め，ポルトガル船の来航を禁じるにあたり，幕府では朱印船貿易の復活が議論された。しかし，ポルトガルと敵対関係になると，東南アジアでの朱印船航行の安全に不安があったため断念した。こうしてできあがった体制を鎖国②とよんでいる。その後，オランダ船との貿易が急増し，中国船の来航もしだいに増加していった。
　鎖国によって，日本に来航するのはオランダ船と中国船に限られ，開港場は長崎③のみになった。ただし，朝鮮とは対馬藩を，琉球とはサツ摩藩を介して貿易が行われた。アイヌの人々とも，松前藩を介して交易が行われた。
　出島のオランダ商館は，オランダ東インド会社の拠点であったバタヴィア(現在のジャカルタ)の支店である。幕府は商館長の毎年交代を命じ，来航のたびに，海外の事情を記したオランダ風説書を提出することを義務づけた。また商館長は，毎年江戸に参府した。商館付きの医師として来日した人のなかには，ヨーロッパの文化を伝えたり，日本の事情を研究して帰国するものもいた①。
　中国では，17世紀半ばに明がほろび，中国東北部からおこった満州(女真)族が南下して清を建国した。明の遺臣鄭芝龍は，幕府に明朝救援を要請し，芝龍の子鄭成功(国姓爺)は，台湾をオランダから奪取して，日本へさかんに貿易船を派遣した②。清は，鄭氏との対抗策として海禁政策をとったが，鄭氏が清にくだったためそれを廃した(展海令)。そのため，中国船の来航は増え，貿易額は増大した。1685(貞享2)年，幕府は，金銀の流出を抑えるため，オランダ船・中国船の輸入額を制限し③，1688(元禄元)年には中国船の来航を年間70隻にかぎった。また，同年，長崎の町に雑居していた中国人を唐人屋敷とよばれる一区域に居住させることにした。
　オランダ船・中国船は，おもに中国産の生糸・絹織物・書籍や，南洋産の砂糖・蘇木・香料・獣皮などをもたらした。日本は，対価として金・銀を支払ったが，金・銀の流出が問題になると，銅や俵物とよばれる海産物を輸出するようになった。

②オランダ商館長付の医師ケンペルがあらわした『日本誌』はヨーロッパで広く普及した。1801(享和元)年，オランダ通詞の志筑忠雄が抄訳し，『鎖国論』としたのが鎖国という言葉の初出である。
③長崎は，旗本が任命される長崎奉行が管轄し，貿易の実務は長崎の町人である地役人があたった。通訳として，オランダ通詞や唐通事がいた。
①オランダ商館長による江戸参府は，1633(寛永10)年以降，毎年行われ，江戸時代を通じて166回を数えた。1790(寛政2)年からは，貿易半減にともない4年に1度になった。
②鄭成功らの中国船は，中国情勢を報ずる唐船風説書を提出した。これはのちに清船にも引き継がれた。これらはのちに『華夷変態』という書物にまとめられた。
③糸割符制度は，1655(明暦元)年に一時廃されて相対自由貿易とされたが，1685(貞享2)年に復活し，年間貿易額がオランダ船は銀3000貫目，中国船は銀6000貫目に制限された。

●朝鮮・琉球と蝦夷地
　己酉約条以後，対馬藩は朝鮮との貿易を独占するとともに，朝鮮との外交業務を幕府に代わって行った。朝鮮からの輸入品は朝鮮人参や木綿で，日本からは銀・銅などが輸出された。朝鮮からは，江戸時代を通じて12回の使節が来日した。前3回は，朝鮮侵略における朝鮮人捕虜の返還を目的とした使節で，4回目からは通信使とよばれた。朝鮮通信使は，300〜500人の使節団で，正使には地位の高い人物が任命された。派遣の名目は，新将軍就任を慶賀するものだったが，日本の国情視察も重要な目的であった。
　琉球は，独立の王国の形をとり，明，ついで清との朝貢貿易を継続した。サツ摩藩は，琉球との独占的な交易によって，中国からの輸入品を入手するとともに，琉球の砂糖を上納させた。また琉球国王は，将軍の代替わりごとに慶賀使を，王の代替わりごとに謝恩使を幕府に派遣した④。
　蝦夷地の南端を支配する松前藩⑤は，領内で米がとれないため，知行の代わりに特定場所でのアイヌとの交易権を家臣たちに与えていた(商場知行制)。このため，本土で産出された食料や衣服と昆布・鮭などの海産物や毛皮などとの交易がさかんに行われていた。アイヌは，松前藩の不当な交易に不満をもっており，1669(寛文9)年，漁猟権をめぐるアイヌ内部の争いを契機に首長シャクシャインを頭にして松前藩と戦った。松前藩は，津軽藩などの協力を得て，これを鎮圧した。これをシャクシャインの戦いという。この戦いの後，アイヌは全面的に松前藩の支配下におかれることになった。

④琉球使節には異国風の服装をさせ，幕府の威信を高めようとした。
⑤蝦夷地南部を統一した蠣崎慶広は，秀吉や家康から蝦夷地における交易権を認められ，松前と改姓し，1万石に相当する大名として遇された。

〈史料〉
松前藩のアイヌ交易
松前殿御仕方も惣て悪しくござ候、米弐斗入の俵も、唯今は七・八升計入れ、大分の押買なされ候、其上俵物にあたり、串貝の一束もたり申さず候へば、来年は二十束にてとられ、出来兼申す夷は子供しちにとられ申し候、諸事の仕方左様にござ候て、夷共難儀に及び申し候、	（津軽一統志）

              </dtext>
            </doc><doc>
              <did>
                PE-20
              </did>
              <dtitle>
                （6）地球環境問題
              </dtitle>
              <dtext>
                
（6）地球環境問題

Ａ　地球環境の汚染はどのように進んでいるのだろうか。
Ｂ　地球環境を破壊せずに，どうすれば開発を進められるだろう。
Ｃ　今まで，地球環境の保護のために，何がなされてきたのか。

●地球環境問題とは
　科学の力をもって自然に挑戦し，その姿を変えてきた人類は，自らの生存を支えてきた地球の生態系の破壊を導いている。産業の発展や開発の進展が引き起こした地球環境全体にかかわる破壊や汚染は，人類全体の問題として注目されるようになった。
　工場施設や交通手段が排出する二酸化炭素やメタンガスは大気圏を温室化する効果をもち，その結果，地球温暖化を引き起こし，将来的に，海面の上昇などの大きな変化を引き起こす可能性が危惧されている。窒素酸化物や硫黄酸化物の排出は，酸性雨の主要な原因となっている。また，人類にとって貴重な酸素供給源となってきた熱帯林の減少も進行している。
　太陽光線の中に含まれる人類にとって有害な紫外線は，オゾン層の存在によってその影響が緩和されてきたが，エアコンや冷蔵庫などに必要とされたフロンガスによってオゾン層の破壊が進んでいる。その結果，紫外線による皮膚がんの多発化などの深刻な影響が懸念されている。
　枯渇が心配される石油や石炭といった化石燃料にかわるものとして開発されてきた原子力エネルギーも，環境破壊を引き起こす要因の一つに数えられる。特に，1986年に旧ソ連のチェルノブイリ原子力発電所で起きた事故は，広範囲にわたる放射能による環境汚染へとつながった。わが国でも，1999年に東海村のウラン加工施設で重大な被ばく事故が起こった。原子力発電などが生み出す放射性廃棄物も，環境汚染の原因となりうる。また，核保有国による核実験は，珊瑚礁などの破壊をもたらしている。
　人類による乱獲のみならず，森林の伐採や環境汚染による生息地の破壊によって絶滅に導かれた生物（絶滅種）と，現在絶滅が危惧されている生物（絶滅危惧種）は，膨大な数にのぼる（野生生物種の減少）。また，過剰な家畜の放牧や，森林伐採，熱帯林の減少は，砂漠化を進展させている。

●地球環境保護の取り組み
　地球環境の破壊を回避するための国際的な試みは，すでに1970年代からみられた。113か国の政府代表が参加した1972年の国連人間環境会議では，人間環境宣言を採択して，地球環境の保護が人類共通の目的であることを確認した。これを受けて，同年，国連総会は，この目的を実現する機関として国連環境計画（UNEP）を設置することを決議した。こうして，それぞれの環境問題について，国連などを中心に国際協力が精力的に試みられた。国際協力の事例として，ラムサール条約①やワシントン条約②などがあげられる。
　冷戦が終焉し，東西対立が解消されると，このような国際協力の試みは加速化された。1992年には，172か国の政府代表とNGOからも2400人におよぶ代表が参加して，国連環境開発会議（地球サミット）が開催され，気候変動枠組み条約（地球温暖化防止条約）などが調印された。地球環境保護のための具体的な行動計画である「アジェンダ21」も採択され，地球環境保護のための国際的枠組みがつくられた。

①ラムサール条約　水鳥の保護を目的に，特に，渡り鳥など水鳥の生息地として国際的に重要な湿地を登録・保護することを義務づけている。日本では釧路湿原などが登録されている。
②ワシントン条約　種の保存のために，絶滅の恐れがある野生動植物の取り引きを規制する。正式名称は「絶滅のおそれのある野生動植物の種の国際取引に関する条約」。

●地球環境と利害対立
　地球環境保護のための国際協調が進められる一方で，環境保護のあり方をめぐって，各国は顕著な利害対立もみせた。最も重要であるのは，発展途上国と先進工業国との対立である。先進工業国は，地球環境の保全のために，途上国における開発や資源の利用に対する国際管理を主張する。しかし，このことは，開発の促進を重視し，環境破壊の主因を先進工業国による資源と自然の濫用にあるとする途上国との利害対立を生み出した。
　この対立に対処する方法として，「持続可能な開発」という考え方がある。これは，環境の維持を妨げることなく発展途上国の開発を進めるというもので，1997年に開催された国連環境開発特別総会では，その実現のための具体的な目標が提起された。しかし，持続可能な開発に関する世界サミット（ヨハネスブルク会議）でも各国の利害対立が表面化した。先進工業諸国間でも環境保護政策が国内経済に与える影響をめぐって対立があり，二酸化炭素の排出量を削減することを決めた京都議定書からは，アメリカが脱退した。今後もこれらの対立は，地球環境問題を解決する方法を模索する上で，常に考慮されなければならない問題であり続けるであろう。

●地球環境保護の主体
　地球環境の保全が必要であるという認識は，地球規模で共有されるようになったものの，依然として国家間には国益の対立がある。この国益の対立をどのように調整するかに，今後の地球環境問題に対する取り組みの成否がかかっているといってよい。
　国益を代表し，その実現をめぐって政府代表が対立しあう一方で，地球環境問題の解決に向けて，国益にとらわれない試みを行っているのがNGOである。地球サミットでも，きわめて多数のNGO代表が参加し，重要な役割を果たした。これらは環境NGOとよばれ，多様な問題に独自の取り組みを行い，国連の場を通じて各国政府に対して重要な影響力を発揮している。
　地球環境問題は市民一人ひとりの生存に，きわめて密接にかかわる問題である以上，市民が主体となってその解決をはかる努力が試みられるべきであろう。地球環境を破壊へと導いている主体は，実は，市民一人ひとりであるといっても過言ではない。二酸化炭素の排出量にしても，野生生物の保全にしても，フロンガスの使用にしても，個々人の日常生活のあり方と密接にかかわっている。地球環境を破壊へと導いている主体こそが，地球環境保全を推進する最も中心的な主体として，生活様式の改変を含め何ができるのかを，身近なところから考え，実行することが重要である。

              </dtext>
            </doc><doc>
              <did>
                MS-4
              </did>
              <dtitle>
                調べよう・考えよう4
              </dtitle>
              <dtext>
                
調べよう・考えよう4
日常生活と宗教や芸術とのかかわり
▼宗教と人生
　左の写真は，一見すると結婚式の絵に見える。しかし，右端に「昭和20年７月20日戦死」と記され，上には「奉納」の文字がある。これは実は，戦死した未婚の息子の成仏と幸せを願って奉納された「ムカサリ絵馬」というものである。ムカサリとは嫁を「迎える」という意味である。
　幼い子が亡くなると，浅く埋葬するなど，死者の世界に行かずに生まれ変わることを願う風習もいろいろとあった。右の写真は「菩提車」である。この菩提車を通りすがりの人が回すことによって，子への供養になるという。
　今日の日本人は，特定の宗教を信じているという者は，成人の三人に一人にすぎないという。確かに，正月や盆は宗教的な意味よりも休みの意味が強くなっているなど，日常生活のなかで宗教を意識する機会は減ってきているようにみえる。
　しかし，結婚式を無宗教でする人はそれほど多くないし，葬式や墓参りには，宗教を意識することが多いであろう。宗教が葬式だけのものになってしまった，という批判もある。しかしわたしたちにとって，ふだんあまり意識しない，しかしだれにも避けることはできない「死」に向きあうとき，そこに宗教との出会いがあることの意味も考えてみたい。そこには，宗教がわたしたちの生活や人生にどのような意味をもち，役割を果たしているかを考えるヒントがあるのではないだろうか。
生活のなかの宗教
　宗教を信じていないとする人でも，さまざまな宗教行事にかかわることは多い。正月や盆のように，毎年くり返して訪れる行事を年中行事という。また，成年（成人）式，結婚式，葬式など，人生のある時点で経験する儀礼を，通過儀礼という。通過儀礼には，大人や社会人，祖霊といった，ある集団への加入式（イニシエーション）という意味がある。
　年中行事も通過儀礼も，その多くが宗教的な意味をもっていた。たとえば正月は，「年神様」を迎える行事である。門松は年神様を招き入れる目印（依代），注連飾りは禍神（わざわいをなす神）が入ってこないようにする呪い，鏡餅は年神様への供え物，というように，それぞれ意味がある。成人式も，かつては地域や生活習慣によってさまざまな形式があり，地域や家の宗教行事への参加が認められることを重要な要素として含んでいた。結婚式や葬式は，今日でも宗教的儀式としておこなわれることが多い。
　このように，「宗教を信じていない」としながらも，わたしたちのまわりには，宗教的な行事は多く残っている。しかも，それらは毎年の暮らしや人生の節目にあたり，大きな意味をもち続けている。
宗教とは何か
　古代の人々は，天体や気象や生命現象などについて，科学的な知識をもたなかった。そのために，多くの自然現象について，その働きやできごとをもたらすものとしての神々が想定された。また，自分たちはどこから来たかということについても知識をもたなかったから，祖先にあたる存在も神々ととらえられた。こうして，多くの古代宗教は，多神教となった。当時の人々は，このように想定された神々を崇拝し，自然の恵みを豊かに得られるように，災害や病気から逃れられるようにと願ったのである①。
　今日わたしたちは，科学や技術が発達した社会に住んでいる。そのために，さまざまな自然現象について，その説明を知るようになった。作物を豊かに実らせたり，災害を防いだり，病気を治したりするのも，科学や技術の仕事になった。では，宗教の役目はもう終わったのだろうか。
　確かに，多くの日本人には宗教を信じているという自覚はない。しかし，身近には多くの宗教的意味のあるものごとがたくさんある。また，世界的にみても，決して宗教はなくなってはいない。それは，今日の科学や技術をもってしても，わからないこと，どうにもならないことが，まだたくさん残っているからである。とりわけ，未来のことは一寸先も確実に予見することはできないし，また結局のところわたしたちはやがて老い，あるいは病んで死んでいくという，人間の一生は変わっていない。このような，人間の有限性に直面したときに，考え方や生き方をさし示すものの一つが宗教なのである。
　なお，今日の国際社会に生起するテロや戦争が，あたかも宗教対立であるかのようにいわれることも少なくない。しかし，国際政治や国際経済の大きな枠組みのなかで，民族対立や宗教対立が生みだされたり，助長されたりしていることが多い②。また，反社会的な主張をもつ者が集団を動かし，犯罪におよぶ場合，宗教を名乗ることもある③。本当に宗教が対立を生んでいるのか，もし宗教がなければ対立は起こらないのか，わたしたちは，歴史にも学びながら冷静に判断しなければならない。
三大世界宗教
　仏教，キリスト教，イスラム教（イスラーム）は，民族や国家をこえて広く世界の人々の間に広まっており，三大世界宗教とよばれる。
　仏教は，インドのゴータマ・シッダッタ（ゴータマ・ブッダ）が開いた悟りをもとにして生まれた宗教である。ブッダは王子であったが，民衆の苦しみをみて，その救いのために出家した。仏教は，出家修行を重視する上座部仏教と，衆生の救済を重視する大乗仏教などに分かれる。前者はスリランカやタイなどでさかんで，タイでは今でも一定期間出家して修行し還俗するという形がとられる。日本に伝わったのは後者であり，さらに日本独自の諸宗派に発展している。
　キリスト教は，古代ユダヤ教を母体とし，イエスの出現によって生まれた宗教である。今日ではローマ・カトリック，ギリシャ正教に始まる東方諸教会，プロテスタントの諸教派に分かれ，それぞれに特色をもっているが，同じ聖書に拠って立つものとして，分裂の歴史を乗りこえ，近年は交流もさかんである。
　イスラム教は，アラビアにあらわれた預言者ムハンマド（マホメット）が開いた。西アジアからアフリカ，中央アジア，東ヨーロッパ，東南アジアなどにも伝わった。
宗教と芸術
　芸術もまた，もともとは宗教的なもの，宗教儀礼を構成する要素として生まれ，発達してきた。そこでは音楽は宗教曲であり，絵画は宗教画であった。スポーツも演劇も，神を楽しませるもの，神にささげるものであった。それらは人間に，神秘的なイメージや深い感情のゆさぶりを与えてきた。そこに人間は，日常生活とは違ったもの，すなわち宗教的体験を見いだしてきた。今日では，さまざまな芸術が，表現手段の多様化や複製技術の高度化④にともなって大衆化し，広く日常生活のなかに織りこまれ，宗教とは無関係のものになったように思われる。しかし，芸術にふれることは，日常性をこえたイメージや感情を受け取ることであり，そのような体験が，人間の心の隙間を埋めたり，張りつめた日常にうるおいや癒しをもたらしているのである。
①祭祀を専門につかさどる階級があらわれ，政治（まつりごと）をすることもあった。また，神話が歴史の一部として考えられる場合もあった。
②一般的な大多数の信徒とは異なった立場に立つグループが，対立をあおることがある。そういうグループは，その宗教の成立当初のあり方や考え方を，現実にそのままあてはめようとしたり，特定の教義を取り出して強調したりする集団で，現実の社会と摩擦が生じることもある。
③カルト集団といわれる。宗教以外にも，さまざまなテーマをかかげるものがある。
④かつては集団に共有され，作者もあいまいなことが多かった諸芸術は，やがて作家の個性を重視するものとなり，今日では著作権の尊重と保護が求められている。一方で，大量の高度な複製品の登場により，従来の芸術のあり方が変化してきている。


              </dtext>
            </doc>
        </docs>
        </annotation>
        </annotations>
        </question>
    </questions>